CHANGELOG.txt
LICENSE.txt
MANIFEST.in
README.txt
setup.py
pyspeakflow/__init__.py
pyspeakflow.egg-info/PKG-INFO
pyspeakflow.egg-info/SOURCES.txt
pyspeakflow.egg-info/dependency_links.txt
pyspeakflow.egg-info/top_level.txt