Metadata-Version: 1.1
Name: pyspeakflow
Version: 0.0.1
Summary: This a very simple speak fucntion packege to make voice assistant etc. 
Home-page: UNKNOWN
Author: Raghav Rajput
Author-email: pythoncode0101@gmail.com
License: MIT
Keywords: pyttsx3 speak sapi5
Platform: UNKNOWN
Classifier: Development Status :: 5 - Production/Stable
Classifier: Intended Audience :: Education
Classifier: Operating System :: Microsoft :: Windows :: Windows 10
Classifier: License :: OSI Approved :: MIT License
Classifier: Programming Language :: Python :: 3
